smithed_libraries/__init__.py
smithed_libraries/common.yaml
smithed_libraries/packs/actionbar/README.md
smithed_libraries/packs/actionbar/beet.yaml
smithed_libraries/packs/actionbar/data/smithed.actionbar/advancement/impl/vanilla/bed/clicked_bed.json
smithed_libraries/packs/actionbar/data/smithed.actionbar/advancement/impl/vanilla/bed/slept_in_bed.json
smithed_libraries/packs/actionbar/data/smithed.actionbar/advancement/impl/vanilla/container/clicked_lockable_block.json
smithed_libraries/packs/actionbar/data/smithed.actionbar/function/impl/display.mcfunction
smithed_libraries/packs/actionbar/data/smithed.actionbar/function/impl/message.mcfunction
smithed_libraries/packs/actionbar/data/smithed.actionbar/function/impl/reset.mcfunction
smithed_libraries/packs/actionbar/data/smithed.actionbar/function/impl/technical/load.mcfunction
smithed_libraries/packs/actionbar/data/smithed.actionbar/function/impl/technical/tick.mcfunction
smithed_libraries/packs/actionbar/data/smithed.actionbar/function/impl/vanilla/bed/check_sleep_status.mcfunction
smithed_libraries/packs/actionbar/data/smithed.actionbar/function/impl/vanilla/bed/clicked_bed.mcfunction
smithed_libraries/packs/actionbar/data/smithed.actionbar/function/impl/vanilla/bed/get_server_status.mcfunction
smithed_libraries/packs/actionbar/data/smithed.actionbar/function/impl/vanilla/bed/send_sleep_status.mcfunction
smithed_libraries/packs/actionbar/data/smithed.actionbar/function/impl/vanilla/bed/show_sleep_percentage.mcfunction
smithed_libraries/packs/actionbar/data/smithed.actionbar/function/impl/vanilla/bed/track_leave_bed.mcfunction
smithed_libraries/packs/actionbar/data/smithed.actionbar/function/impl/vanilla/container/check_double_chest_lock/east.mcfunction
smithed_libraries/packs/actionbar/data/smithed.actionbar/function/impl/vanilla/container/check_double_chest_lock/north.mcfunction
smithed_libraries/packs/actionbar/data/smithed.actionbar/function/impl/vanilla/container/check_double_chest_lock/south.mcfunction
smithed_libraries-0.16.3.dist-info/LICENSE
smithed_libraries-0.16.3.dist-info/WHEEL
smithed_libraries-0.16.3.dist-info/METADATA
smithed_libraries-0.16.3.dist-info/RECORD
