Metadata-Version: 2.1
Name: smithed-libraries
Version: 0.16.3
Summary: All of the Smithed Libraries
License: MIT
Author: Smithed Council
Author-email: team@smithed.dev
Requires-Python: >=3.10,<4.0
Classifier: License :: OSI Approved :: MIT License
Classifier: Programming Language :: Python :: 3
Classifier: Programming Language :: Python :: 3.10
Classifier: Programming Language :: Python :: 3.11
Requires-Dist: beet (>=0.108.5)
Requires-Dist: bolt (>=0.49.0,<0.50.0)
Requires-Dist: bolt-expressions (>=0.17.0,<0.18.0)
Requires-Dist: mecha (>=0.95.0,<0.96.0)
Requires-Dist: pydantic (>=2.5.2,<3.0.0)
Requires-Dist: rich (>=13.9.2,<14.0.0)
